{
  "bhom": {
    "event_count": 1000,
    "path": "data/BHOM_20260423110000-20260423120000.json",
    "reported_total": 1663,
    "responses": 1
  },
  "bhom_to_truesight": {
    "ambiguous_count": 4,
    "coverage_pct": 19.33,
    "critical_events_in_bhom": 150,
    "critical_match_pct": 18.67,
    "matched_count": 29,
    "matched_to_critical_count": 28,
    "matched_to_noncritical_count": 1,
    "top_unmatched_object_classes": [
      {
        "count": 73,
        "object_class": "HELIX_COMPONENT"
      },
      {
        "count": 25,
        "object_class": "UNKNOWN"
      },
      {
        "count": 18,
        "object_class": "NUK_FileSystem"
      },
      {
        "count": 1,
        "object_class": "IAK_CPU"
      }
    ],
    "unmatched_count": 117
  },
  "issues": [
    {
      "kind": "partial_export",
      "materialized_hits": 1000,
      "message": "Export contains fewer materialized hits than the reported total.",
      "reported_total": 1663,
      "source": "bhom"
    }
  ],
  "truesight": {
    "event_count": 1478,
    "parser": "baroc",
    "path": "data/truesight_20260423110000-20260423120000.baroc"
  },
  "truesight_to_bhom": {
    "ambiguous_count": 5,
    "coverage_pct": 70.27,
    "critical_events_in_truesight": 74,
    "critical_match_pct": 59.46,
    "matched_count": 52,
    "matched_to_critical_count": 44,
    "matched_to_noncritical_count": 8,
    "top_unmatched_object_classes": [
      {
        "count": 6,
        "object_class": "CONTROLM_Enterprise_Manager"
      },
      {
        "count": 2,
        "object_class": "CHECK_NON_EVENT"
      },
      {
        "count": 2,
        "object_class": "HTTP-create_event_json"
      },
      {
        "count": 2,
        "object_class": "MANUAL_EVENT"
      },
      {
        "count": 2,
        "object_class": "NUK_FileSystem"
      },
      {
        "count": 2,
        "object_class": "WH_POSTGRES"
      },
      {
        "count": 1,
        "object_class": "SCOM_CONNECT"
      }
    ],
    "unmatched_count": 17
  }
}